README.md
setup.py
peliqan/__init__.py
peliqan/core.py
peliqan/exceptions.py
peliqan/test.py
peliqan/utils.py
peliqan.egg-info/PKG-INFO
peliqan.egg-info/SOURCES.txt
peliqan.egg-info/dependency_links.txt
peliqan.egg-info/requires.txt
peliqan.egg-info/top_level.txt
peliqan/client/__init__.py
peliqan/client/aiclient.py
peliqan/client/backend_service.py
peliqan/client/base.py
peliqan/client/dbclient.py
peliqan/client/sftpclient.py
peliqan/client/writeback.py