Metadata-Version: 2.4
Name: peliqan
Version: 2.16.0
Summary: This package is an sdk that allows any python client to connect with a Peliqan environment.
Home-page: https://peliqan.io/
Author: Peliqan.io
Author-email: dev@peliqan.io
License: MIT
Classifier: Development Status :: 4 - Beta
Classifier: Intended Audience :: Customer Service
Classifier: Intended Audience :: Developers
Classifier: License :: OSI Approved :: MIT License
Classifier: Operating System :: POSIX :: Linux
Classifier: Operating System :: MacOS :: MacOS X
Classifier: Operating System :: Microsoft :: Windows
Classifier: Programming Language :: Python :: 3 :: Only
Requires-Dist: pandas
Requires-Dist: requests
Requires-Dist: openai
Dynamic: author
Dynamic: author-email
Dynamic: classifier
Dynamic: home-page
Dynamic: license
Dynamic: requires-dist
Dynamic: summary
